windowpops/SplashConfig.py
windowpops/SplashScreen_Dark.py
windowpops/SplashScreen_Growing.py
windowpops/SplashScreen_Load.py
windowpops/SplashScreen_Transparent.py
windowpops/TextBarfy.py
windowpops/__init__.py
windowpops/ext/SplashScreen_DarkEx.py
windowpops/ext/SplashScreen_GrowingEx.py
windowpops/ext/SplashScreen_LoadEx.py
windowpops/ext/SplashScreen_TransparentEx.py
windowpops/ext/__init__.py
windowpops-2.0.1.dist-info/License.txt
windowpops-2.0.1.dist-info/METADATA
windowpops-2.0.1.dist-info/WHEEL
windowpops-2.0.1.dist-info/top_level.txt
windowpops-2.0.1.dist-info/RECORD
