Metadata-Version: 2.1
Name: windowpops
Version: 2.0.1
Summary: I have developed a user-friendly graphical interface (GUI) built with PyQt5, a powerful Python library designed for creating desktop applications with native-looking elements on Windows, macOS, and Linux. This interface empowers you to interact with various applications from a single, centralized location.
Home-page: 
Author: robert kimts
Author-email: robertskimts@outlook.com
License: MIT
License-File: License.txt
